CHANGELOG.rst
LICENCE.rst
aleksis/apps/evalu/__init__.py
aleksis/apps/evalu/admin.py
aleksis/apps/evalu/apps.py
aleksis/apps/evalu/forms.py
aleksis/apps/evalu/frontend/index.js
aleksis/apps/evalu/frontend/messages/de.json
aleksis/apps/evalu/frontend/messages/en.json
aleksis/apps/evalu/frontend/messages/ru.json
aleksis/apps/evalu/frontend/messages/uk.json
aleksis/apps/evalu/locale/.keepdir
aleksis/apps/evalu/locale/ar/LC_MESSAGES/django.mo
aleksis/apps/evalu/locale/ar/LC_MESSAGES/django.po
aleksis/apps/evalu/locale/ar/LC_MESSAGES/djangojs.mo
aleksis/apps/evalu/locale/ar/LC_MESSAGES/djangojs.po
aleksis/apps/evalu/locale/de_DE/LC_MESSAGES/django.mo
aleksis/apps/evalu/locale/de_DE/LC_MESSAGES/django.po
aleksis/apps/evalu/locale/de_DE/LC_MESSAGES/djangojs.mo
aleksis/apps/evalu/locale/de_DE/LC_MESSAGES/djangojs.po
aleksis/apps/evalu/locale/fr/LC_MESSAGES/django.mo
aleksis/apps/evalu/locale/fr/LC_MESSAGES/django.po
aleksis/apps/evalu/locale/fr/LC_MESSAGES/djangojs.mo
aleksis/apps/evalu/locale/fr/LC_MESSAGES/djangojs.po
aleksis/apps/evalu/locale/la/LC_MESSAGES/django.mo
aleksis/apps/evalu/locale/la/LC_MESSAGES/django.po
aleksis/apps/evalu/locale/la/LC_MESSAGES/djangojs.mo
aleksis/apps/evalu/locale/la/LC_MESSAGES/djangojs.po
aleksis/apps/evalu/locale/nb_NO/LC_MESSAGES/django.mo
aleksis/apps/evalu/locale/nb_NO/LC_MESSAGES/django.po
aleksis/apps/evalu/locale/nb_NO/LC_MESSAGES/djangojs.mo
aleksis/apps/evalu/locale/nb_NO/LC_MESSAGES/djangojs.po
aleksis/apps/evalu/locale/ru/LC_MESSAGES/django.mo
aleksis/apps/evalu/locale/ru/LC_MESSAGES/django.po
aleksis/apps/evalu/locale/ru/LC_MESSAGES/djangojs.mo
aleksis/apps/evalu/locale/ru/LC_MESSAGES/djangojs.po
aleksis/apps/evalu/locale/tr_TR/LC_MESSAGES/django.mo
aleksis/apps/evalu/locale/tr_TR/LC_MESSAGES/django.po
aleksis/apps/evalu/locale/tr_TR/LC_MESSAGES/djangojs.mo
aleksis/apps/evalu/locale/tr_TR/LC_MESSAGES/djangojs.po
aleksis/apps/evalu/locale/uk/LC_MESSAGES/django.mo
aleksis/apps/evalu/locale/uk/LC_MESSAGES/django.po
aleksis_app_evalu-2.0.2.post0.dist-info/METADATA
aleksis_app_evalu-2.0.2.post0.dist-info/WHEEL
aleksis_app_evalu-2.0.2.post0.dist-info/entry_points.txt
aleksis_app_evalu-2.0.2.post0.dist-info/RECORD
