Metadata-Version: 2.1
Name: AlekSIS-App-EvaLU
Version: 2.0.2.post0
Summary: Unofficial AlekSIS App EvaLU (Evaluation of teaching and lesson quality)
Home-page: https://edugit.org/katharineum/AlekSIS-App-EvaLU
License: EUPL-1.2-or-later
Author: Jonathan Weth
Author-email: dev@jonathanweth.de
Maintainer: Jonathan Weth
Maintainer-email: dev@jonathanweth.de
Requires-Python: >=3.9,<4.0
Classifier: Environment :: Web Environment
Classifier: Intended Audience :: Education
Classifier: License :: Other/Proprietary License
Classifier: Programming Language :: Python :: 3
Classifier: Programming Language :: Python :: 3.9
Classifier: Programming Language :: Python :: 3.10
Classifier: Programming Language :: Python :: 3.11
Classifier: Topic :: Education
Requires-Dist: aleksis-app-chronos (>=3.0,<4.0)
Requires-Dist: aleksis-core (>=3.0,<4.0)
Requires-Dist: cryptography (>=41.0.0,<42.0.0)
Requires-Dist: django-formtools (>=2.3,<3.0)
Project-URL: Repository, https://edugit.org/katharineum/AlekSIS-App-EvaLU
